tckn.py
tckn-1.1.0.dist-info/LICENSE
tckn-1.1.0.dist-info/WHEEL
tckn-1.1.0.dist-info/METADATA
tckn-1.1.0.dist-info/RECORD
